[
  { "tile_id": "A3_static", "from": "SE", "to": "PLE", "income": -1 },
  { "tile_id": "A7_static", "from": "S", "to": "TERMINAL", "income": -1 },
  { "tile_id": "A13_static", "from": "NE", "to": "TERMINAL", "income": -1 },
  { "tile_id": "B2_static", "from": "S", "to": "TERMINAL", "income": -1 },
  { "tile_id": "B14_static", "from": "NE", "to": "TERMINAL", "income": -1 },
  { "tile_id": "B14_static", "from": "N", "to": "TERMINAL", "income": -1 },
  { "tile_id": "E1_static", "from": "SW", "to": "SE", "income": 0 },
  { "tile_id": "E1_static", "from": "SE", "to": "SW", "income": -1 },
  { "tile_id": "F14_static", "from": "SW", "to": "SE", "income": 0 },
  { "tile_id": "F14_static", "from": "SE", "to": "SW", "income": 0 },
  { "tile_id": "G1_static", "from": "SW", "to": "S", "income": 0 },
  { "tile_id": "G1_static", "from": "SW", "to": "SE", "income": 0 },
  { "tile_id": "H6_initial", "from": "NE", "to": "CITY", "income": 30 },
  { "tile_id": "H6_initial", "from": "SW", "to": "B&O", "income": 30 },
  { "tile_id": "H14_static", "from": "NW", "to": "TERMINAL", "income": -1 },
  { "tile_id": "I9_static", "from": "N", "to": "SE", "income": 30 },
  { "tile_id": "I9_static", "from": "SE", "to": "N", "income": 30 },
  { "tile_id": "J4_initial", "from": "N", "to": "CITY", "income": 30 },
  { "tile_id": "J4_initial", "from": "S", "to": "CITY", "income": 30 },
  { "tile_id": "K1_static", "from": "SW", "to": "S", "income": 30 },
  { "tile_id": "K1_static", "from": "S", "to": "SW", "income": 30 },
  { "tile_id": "K7_static", "from": "N", "to": "NW", "income": 0 },
  { "tile_id": "K7_static", "from": "NW", "to": "N", "income": 0 },
  { "tile_id": "L2_static", "from": "S", "to": "TERMINAL", "income": -1 },
  { "tile_id": "L2_static", "from": "SW", "to": "TERMINAL", "income": -1 },
  { "tile_id": "X1", "from": "S", "to": "NE", "income": 30 },
  { "tile_id": "X1", "from": "NE", "to": "S", "income": 30 },
  { "tile_id": "9", "from": "S", "to": "N", "income": 0 },
  { "tile_id": "9", "from": "N", "to": "S", "income": 0 }
]
